abit_clustering.py
abit_clustering-1.1.0.dist-info/licenses/LICENSE
abit_clustering-1.1.0.dist-info/METADATA
abit_clustering-1.1.0.dist-info/WHEEL
abit_clustering-1.1.0.dist-info/top_level.txt
abit_clustering-1.1.0.dist-info/RECORD
