Metadata-Version: 2.4
Name: abit-clustering
Version: 1.1.0
Summary: Adaptive Binary Iterative Threshold Clustering implementation
Author-email: John Ades <john.a.ades@gmail.com>
License: MIT License
Project-URL: Homepage, https://github.com/john-ades/abit-clustering
Project-URL: Issues, https://github.com/john-ades/abit-clustering/issues
Classifier: Programming Language :: Python :: 3
Classifier: License :: OSI Approved :: MIT License
Classifier: Operating System :: OS Independent
Requires-Python: >=3.7
License-File: LICENSE
Requires-Dist: numpy
Dynamic: license-file
